{
    "item":[
        {
            "fid" : 1,
            "id" : 1,
            "descriptionImage" : "neoc.jpeg"

        },
        {
            "fid" : 2,
            "id" : 2,
            "descriptionImage" : "neoa.jpeg"
        },
        {
            "fid" : 3,
            "id" : 3,
            "descriptionImage" : "neov.jpeg"
        },
        {
            "fid" : 4,
            "id" : 4,
            "descriptionImage" : "pimafix.jpeg"
        },
        {
            "fid" : 5,
            "id" : 5,
            "descriptionImage" : "melafix.jpeg"
        },
        {
            "fid" : 6,
            "id" : 6,
            "descriptionImage" : "flourishexel.jpeg"
        }
    ]
}